rag_shared/__init__.py
rag_shared-0.1.5.dist-info/METADATA
rag_shared-0.1.5.dist-info/WHEEL
rag_shared-0.1.5.dist-info/top_level.txt
rag_shared-0.1.5.dist-info/RECORD
