Metadata-Version: 2.4
Name: rag_shared
Version: 0.1.5
Summary: Azure-native RAG Framework with System-Assigned Managed Identity support
Author-email: Your Name <your.email@example.com>
License: MIT
Project-URL: Homepage, https://github.com/nunot/RAG_Framework
Project-URL: Repository, https://github.com/nunot/RAG_Framework
Classifier: Development Status :: 4 - Beta
Classifier: Intended Audience :: Developers
Classifier: Programming Language :: Python :: 3
Classifier: Programming Language :: Python :: 3.9
Classifier: Programming Language :: Python :: 3.10
Classifier: Programming Language :: Python :: 3.11
Requires-Python: >=3.9
Requires-Dist: PyYAML
Requires-Dist: azure-identity
Requires-Dist: azure-keyvault-secrets
Requires-Dist: azure-search-documents
Requires-Dist: openai
Requires-Dist: httpx
Requires-Dist: asyncpg
Requires-Dist: pyodbc
Requires-Dist: jinja2
Requires-Dist: dacite
